AUTHORS.rst
CHANGELOG.rst
LICENSE
MANIFEST.in
README.rst
setup.py
django_snippetscream.egg-info/PKG-INFO
django_snippetscream.egg-info/SOURCES.txt
django_snippetscream.egg-info/dependency_links.txt
django_snippetscream.egg-info/not-zip-safe
django_snippetscream.egg-info/top_level.txt
snippetscream/_1031.py
snippetscream/_1378.py
snippetscream/_186.py
snippetscream/_1875.py
snippetscream/_2240.py
snippetscream/_2536.py
snippetscream/_963.py
snippetscream/__init__.py
snippetscream/csv_serializer.py
snippetscream/models.py
snippetscream/tests/__init__.py
snippetscream/tests/urls.py