Metadata-Version: 1.0
Name: django-snippetscream
Version: 0.0.7
Summary: Django app packaging the best snippets found on http://djangosnippets.org
Home-page: http://github.com/shaunsephton/django-snippetscream
Author: Shaun Sephton
Author-email: shaunsephton@gmail.com
License: UNKNOWN
Platform: UNKNOWN
Classifier: Programming Language :: Python
Classifier: License :: OSI Approved :: BSD License
Classifier: Development Status :: 4 - Beta
Classifier: Operating System :: OS Independent
Classifier: Framework :: Django
Classifier: Intended Audience :: Developers
Classifier: Topic :: Internet :: WWW/HTTP :: Dynamic Content
